main.py
setup.py
dbt_byteshouse.egg-info/PKG-INFO
dbt_byteshouse.egg-info/SOURCES.txt
dbt_byteshouse.egg-info/dependency_links.txt
dbt_byteshouse.egg-info/requires.txt
dbt_byteshouse.egg-info/top_level.txt